{
	"name": "gold_sql_hechos_ventas",
	"properties": {
		"linkedServiceName": {
			"referenceName": "sql_dw_store_sales",
			"type": "LinkedServiceReference"
		},
		"folder": {
			"name": "GOLD"
		},
		"annotations": [],
		"type": "AzureSqlTable",
		"schema": [
			{
				"name": "id",
				"type": "int",
				"precision": 10
			},
			{
				"name": "fecha",
				"type": "date"
			},
			{
				"name": "cliente_id",
				"type": "int",
				"precision": 10
			},
			{
				"name": "producto_id",
				"type": "int",
				"precision": 10
			},
			{
				"name": "cantidad",
				"type": "int",
				"precision": 10
			},
			{
				"name": "precio_unitario",
				"type": "decimal",
				"precision": 18,
				"scale": 0
			},
			{
				"name": "total_venta",
				"type": "decimal",
				"precision": 18,
				"scale": 0
			}
		],
		"typeProperties": {
			"schema": "GOLD",
			"table": "FACT_VENTAS"
		}
	}
}